pydantic_python_regex_validator/__init__.py
pydantic_python_regex_validator/fast_api.py
pydantic_python_regex_validator/regex.py
pydantic_python_regex_validator-0.3.4.dist-info/METADATA
pydantic_python_regex_validator-0.3.4.dist-info/WHEEL
pydantic_python_regex_validator-0.3.4.dist-info/RECORD
