Metadata-Version: 2.1
Name: pydantic-python-regex-validator
Version: 0.3.4
Summary: A regex validator for pydantic, using python regex.
Home-page: https://github.com/ollz272/pydantic-python-regex-validator
Author: Oli Parker
Author-email: oli.edmund.parker@gmail.com
Requires-Python: >=3.8,<4.0
Classifier: Framework :: FastAPI
Classifier: Framework :: Pydantic
Classifier: Framework :: Pydantic :: 2
Classifier: Intended Audience :: Developers
Classifier: Programming Language :: Python :: 3
Classifier: Programming Language :: Python :: 3.8
Classifier: Programming Language :: Python :: 3.9
Classifier: Programming Language :: Python :: 3.10
Classifier: Programming Language :: Python :: 3.11
Classifier: Programming Language :: Python :: 3 :: Only
Classifier: Topic :: Utilities
Provides-Extra: all
Provides-Extra: fastapi
Requires-Dist: fastapi (>=0.101.1,<0.102.0) ; extra == "all" or extra == "fastapi"
Requires-Dist: pydantic (>=2.0.0,<3.0.0)
Project-URL: Repository, https://github.com/ollz272/pydantic-python-regex-validator
